CONTRIBUTORS.txt
License.txt
MANIFEST.in
README.md
README.rst
THANKS.txt
ez_setup.py
requirements.txt
setup.cfg
setup.py
test.sh
peyutil/__init__.py
peyutil/dict_wrapper.py
peyutil/input_output.py
peyutil/str_util.py
peyutil/tokenizer.py
peyutil.egg-info/PKG-INFO
peyutil.egg-info/SOURCES.txt
peyutil.egg-info/dependency_links.txt
peyutil.egg-info/entry_points.txt
peyutil.egg-info/requires.txt
peyutil.egg-info/top_level.txt
peyutil.egg-info/zip-safe
peyutil/test/__init__.py
peyutil/test/test_init.py
peyutil/test/test_input_output.py
peyutil/test/test_str_util.py
peyutil/test/test_struct_diff.py
peyutil/test/test_tokenizer.py
peyutil/test/data/nexson/not_really_nexson.txt
peyutil/test/data/nexson/study_tree_list.json
peyutil/test/support/__init__.py
peyutil/test/support/helper.py
peyutil/test/support/pathmap.py
peyutil/test/support/struct_diff.py