Metadata-Version: 1.1
Name: peyutil
Version: 0.0.4
Summary: Utility functions used by other python packages written by the  Open Tree of Life team
Home-page: https://github.com/OpenTreeOfLife/peyutil
Author: Emily Jane B. McTavish and Mark T. Holder
Author-email: mtholder@gmail.com
License: BSD
Keywords: bioinformatics,utility,phylogenetics
Platform: UNKNOWN
Classifier: Development Status :: 4 - Beta
Classifier: Intended Audience :: Science/Research
Classifier: Intended Audience :: Developers
Classifier: Natural Language :: English
Classifier: License :: OSI Approved :: BSD License
Classifier: Operating System :: OS Independent
Classifier: Programming Language :: Python :: 2.7
Classifier: Programming Language :: Python :: 3.6
Classifier: Programming Language :: Python :: 3.7
Classifier: Programming Language :: Python :: 3.8
Classifier: Topic :: Scientific/Engineering :: Bio-Informatics
